CHANGELOG.txt
LICENCE.txt
MANIFEST.in
README.txt
setup.py
shehabadd.egg-info/PKG-INFO
shehabadd.egg-info/SOURCES.txt
shehabadd.egg-info/dependency_links.txt
shehabadd.egg-info/top_level.txt
shehaqbAdd/shehab.py